pypi_eg_alebg/__init__.py
pypi_eg_alebg/simple_sum.py
pypi_eg_alebg-0.1.1.dist-info/LICENSE
pypi_eg_alebg-0.1.1.dist-info/METADATA
pypi_eg_alebg-0.1.1.dist-info/WHEEL
pypi_eg_alebg-0.1.1.dist-info/RECORD
