Metadata-Version: 2.1
Name: pypi-eg-alebg
Version: 0.1.1
Summary: Example project to test publishing to PyPI
License: Custom
Author: Luis Alejandro Bordo García
Author-email: bgluiszz@gmail.com
Requires-Python: >=3.10,<4.0
Classifier: License :: Other/Proprietary License
Classifier: Programming Language :: Python :: 3
Classifier: Programming Language :: Python :: 3.10
Classifier: Programming Language :: Python :: 3.11
Classifier: Programming Language :: Python :: 3.12
